<?xml version="1.0" encoding="UTF-8"?>
<csw:Capabilities version="2.0.2" xmlns:csw="http://www.opengis.net/cat/csw/2.0.2" xmlns:gmd="http://www.isotc211.org/2005/gmd" xmlns:gml="http://www.opengis.net/gml" xmlns:ogc="http://www.opengis.net/ogc" xmlns:ows="http://www.opengis.net/ows" xmlns:xlink="http://www.w3.org/1999/xlink" xmlns:xsi="http://www.w3.org/2001/XMLSchema-instance">
	<ows:ServiceIdentification>
		<ows:Title>terraCatalog GDI-DE Testbed</ows:Title>
		<ows:Abstract>terraCatalog GDI-DE Testbed - Version 2.0</ows:Abstract>
		<ows:Keywords>
			<ows:Keyword>CS-W</ows:Keyword>
			<ows:Keyword>ISO19119</ows:Keyword>
			<ows:Keyword>ISO19115</ows:Keyword>
			<ows:Keyword>Catalog Service</ows:Keyword>
			<ows:Keyword>metadata</ows:Keyword>
			<ows:Keyword>INSPIRE</ows:Keyword>
			<ows:Type codeSpace="http://www.conterra.de">theme</ows:Type>
		</ows:Keywords>
		<ows:ServiceType>CSW</ows:ServiceType>
		<ows:ServiceTypeVersion>2.0.2</ows:ServiceTypeVersion>
	</ows:ServiceIdentification>
	<ows:ServiceProvider>
		<ows:ProviderName/>
		<ows:ProviderSite xlink:href="" xlink:type="simple"/>
		<ows:ServiceContact>
			<ows:IndividualName>Dr. Uwe Voges</ows:IndividualName>
			<ows:PositionName/>
			<ows:ContactInfo>
				<ows:Phone>
					<ows:Voice/>
					<ows:Facsimile/>
				</ows:Phone>
				<ows:Address>
					<ows:DeliveryPoint/>
					<ows:City/>
					<ows:AdministrativeArea/>
					<ows:PostalCode/>
					<ows:Country/>
					<ows:ElectronicMailAddress/>
				</ows:Address>
				<ows:OnlineResource xlink:href=""/>
			</ows:ContactInfo>
		</ows:ServiceContact>
	</ows:ServiceProvider>
	<ows:OperationsMetadata>
		<ows:Operation name="GetCapabilities">
			<ows:DCP>
				<ows:HTTP>
					<ows:Get xlink:href="http://gdi-de.sdisuite.de:8080/soapServices/CSWStartup?"/>
					<ows:Post xlink:href="http://gdi-de.sdisuite.de:8080/soapServices/services/CSWDiscovery">
						<ows:Constraint name="PostEncoding">
							<ows:Value>SOAP</ows:Value>
						</ows:Constraint>
					</ows:Post>
				</ows:HTTP>
			</ows:DCP>
		</ows:Operation>
		<ows:Operation name="GetRecords">
			<ows:DCP>
				<ows:HTTP>
					<ows:Post xlink:href="http://gdi-de.sdisuite.de:8080/soapServices/services/CSWDiscovery">
						<ows:Constraint name="PostEncoding">
							<ows:Value>SOAP</ows:Value>
						</ows:Constraint>
					</ows:Post>
					<ows:Post xlink:href="http://gdi-de.sdisuite.de:8080/soapServices/CSWStartup">
						<ows:Constraint name="PostEncoding">
							<ows:Value>XML</ows:Value>
						</ows:Constraint>
					</ows:Post>
				</ows:HTTP>
			</ows:DCP>
			<ows:Parameter name="typeName">
				<ows:Value>gmd:MD_Metadata</ows:Value>
				<ows:Value>csw:Record</ows:Value>
			</ows:Parameter>
			<ows:Parameter name="outputFormat">
				<ows:Value>application/xml</ows:Value>
				<ows:Value>text/xml</ows:Value>
			</ows:Parameter>
			<ows:Parameter name="outputSchema">
				<ows:Value>http://www.opengis.net/cat/csw/2.0.2</ows:Value>
				<ows:Value>http://www.isotc211.org/2005/gmd</ows:Value>
			</ows:Parameter>
			<ows:Parameter name="resultType">
				<ows:Value>hits</ows:Value>
				<ows:Value>results</ows:Value>
				<ows:Value>validate</ows:Value>
			</ows:Parameter>
			<ows:Parameter name="ElementSetName">
				<ows:Value>brief</ows:Value>
				<ows:Value>summary</ows:Value>
				<ows:Value>full</ows:Value>
			</ows:Parameter>
			<ows:Parameter name="CONSTRAINTLANGUAGE">
				<ows:Value>Filter</ows:Value>
			</ows:Parameter>
			<ows:Constraint name="SupportedISOQueryables">
				<ows:Value>RevisionDate</ows:Value>
				<ows:Value>CreationDate</ows:Value>
				<ows:Value>PublicationDate</ows:Value>
				<ows:Value>OrganisationName</ows:Value>
				<ows:Value>Language</ows:Value>
				<ows:Value>ResourceIdentifier</ows:Value>
				<ows:Value>KeywordType</ows:Value>
				<ows:Value>TopicCategory</ows:Value>
				<ows:Value>ResourceLanguage</ows:Value>
				<ows:Value>GeographicDescriptionCode</ows:Value>
				<ows:Value>DistanceValue</ows:Value>
				<ows:Value>DistanceUOM</ows:Value>
				<ows:Value>TempExtent_begin</ows:Value>
				<ows:Value>TempExtent_end</ows:Value>
				<ows:Value>ServiceType</ows:Value>
				<ows:Value>Operation</ows:Value>
				<ows:Value>Denominator</ows:Value>
			</ows:Constraint>
			<ows:Constraint name="AdditionalQueryables">
				<ows:Value>HierarchyLevelName</ows:Value>
				<ows:Value>Degree</ows:Value>
				<ows:Value>ConditionApplyingToAccessAndUse</ows:Value>
				<ows:Value>MetadataPointOfContact</ows:Value>
				<ows:Value>Lineage</ows:Value>
				<ows:Value>SpecificationTitle</ows:Value>
				<ows:Value>SpecificationDate</ows:Value>
				<ows:Value>SpecificationDateType</ows:Value>
				<ows:Value>AccessConstraints</ows:Value>
				<ows:Value>OtherConstraints</ows:Value>
				<ows:Value>Classification</ows:Value>
				<ows:Value>ResponsiblePartyRole</ows:Value>
			</ows:Constraint>
			<!-- enter the supported federated catalogues for distributed search as values below -->
			<ows:Constraint name="FederatedCatalogues">
				<ows:Value/>
			</ows:Constraint>
		</ows:Operation>
		<ows:Constraint name="PostEncoding">
			<ows:Value>SOAP</ows:Value>
		</ows:Constraint>
		<ows:Constraint name="IsoProfiles">
			<ows:Value>http://www.isotc211.org/2005/gmd</ows:Value>
		</ows:Constraint>
		<ows:ExtendedCapabilities>
			<!-- for multilingual catalogues, define additional supported languages here with link to respective capabilities -->
			<ins:MultilingualCapabilities xmlns:ins="http://inspire.europa.eu/networkservice/discovery">
				<!-- </ins:MultilingualCapabilities> xsi:schemaLocation="http://inspire.europa.eu/networkservice/discovery  ../../profiles/inspire/Capabilities.xsd">  -->
				<ins:MetadataUrl>
					<gmd:CI_OnlineResource>
						<gmd:linkage>
							<gmd:URL>http://www...</gmd:URL>
						</gmd:linkage>
					</gmd:CI_OnlineResource>
				</ins:MetadataUrl>
				<ins:CurrentLanguage>
					<ins:Language>ENG</ins:Language>
				</ins:CurrentLanguage>
			</ins:MultilingualCapabilities>
		</ows:ExtendedCapabilities>
	</ows:OperationsMetadata>
	<ogc:Filter_Capabilities>
		<ogc:Spatial_Capabilities>
			<ogc:GeometryOperands>
				<ogc:GeometryOperand>gml:Envelope</ogc:GeometryOperand>
			</ogc:GeometryOperands>
			<ogc:SpatialOperators>
				<ogc:SpatialOperator name="BBOX"/>
				<ogc:SpatialOperator name="Disjoint"/>
				<ogc:SpatialOperator name="Intersects"/>
			</ogc:SpatialOperators>
		</ogc:Spatial_Capabilities>
		<ogc:Scalar_Capabilities>
			<ogc:LogicalOperators/>
			<ogc:ComparisonOperators>
				<ogc:ComparisonOperator>Between</ogc:ComparisonOperator>
				<ogc:ComparisonOperator>EqualTo</ogc:ComparisonOperator>
				<ogc:ComparisonOperator>GreaterThan</ogc:ComparisonOperator>
				<ogc:ComparisonOperator>GreaterThanEqualTo</ogc:ComparisonOperator>
				<ogc:ComparisonOperator>LessThan</ogc:ComparisonOperator>
				<ogc:ComparisonOperator>LessThanEqualTo</ogc:ComparisonOperator>
				<ogc:ComparisonOperator>Like</ogc:ComparisonOperator>
				<ogc:ComparisonOperator>NotEqualTo</ogc:ComparisonOperator>
				<ogc:ComparisonOperator>NullCheck</ogc:ComparisonOperator>
			</ogc:ComparisonOperators>
		</ogc:Scalar_Capabilities>
		<ogc:Id_Capabilities>
			<ogc:FID/>
		</ogc:Id_Capabilities>
	</ogc:Filter_Capabilities>
</csw:Capabilities>


